ucmscraper.py
ucmscraper-2.1.0.dist-info/LICENSE.txt
ucmscraper-2.1.0.dist-info/METADATA
ucmscraper-2.1.0.dist-info/WHEEL
ucmscraper-2.1.0.dist-info/top_level.txt
ucmscraper-2.1.0.dist-info/RECORD
