Metadata-Version: 2.1
Name: ucmscraper
Version: 2.1.0
Summary: Module for scraping UC Merced's class schedules
Home-page: https://github.com/karinassuni/ucmscraper
Author: Karina Antonio
Author-email: karinafantonio@gmail.com
License: MIT
Platform: UNKNOWN
Requires-Dist: cssselect
Requires-Dist: lxml
Requires-Dist: requests
